[
    {
        "id": 1,
        "artist": "Miley Cirus",
        "title": "Decades",
        "album": "Flowers",
        "price": 39.99,
        "description": "Analog sound storage medium in the form of a flat disc with an inscribed, modulated spiral groove.",
        "category": "Clothes",
        "url":["https://m.media-amazon.com/images/I/31WmKkRakeL._SX300_SY300_QL70_FMwebp_.jpg"]
    },
    {
        "id": 2,
        "artist": "Beatles",
        "title": "Postal Service",
        "album": "Abbey Road",    
        "price": 21.99,
        "description": "Analog sound storage medium in the form of a flat disc with an inscribed, modulated spiral groove.",
        "category": "Clothes",
        "url":["https://m.media-amazon.com/images/I/51wqQoqZ7kL._SY300_SX300_QL70_FMwebp_.jpg"]
       
    },
    {
        
        "id": 3,
        "artist": "Kuai Gabino",
        "title": "Someday",
        "album": "Human",
        "price": 59.99,
        "description": "Analog sound storage medium in the form of a flat disc with an inscribed, modulated spiral groove.",
        "category": "Clothes",
        "url":["https://m.media-amazon.com/images/I/213XFYpZtHL._SX300_SY300_QL70_FMwebp_.jpg"]
    },
    {
        "id": 4,
        "artist": "Kygo",
        "title": "Love Somebody",
        "album": "Cloud Nine",
        "price": 51.99,
        "description": "4 LP used like new, analog sound storage medium in the form of a flat disc with an inscribed, modulated spiral groove.",
        "category": "Vinyls",
        "url":["https://m.media-amazon.com/images/I/51kI9lErKWL._SX300_SY300_QL70_FMwebp_.jpg"]
    },
    {
        "id": 5,
        "artist": "Gorillaz",
        "title": "Plsstic Beach",
        "album": "The War",
        "price": 59.99,
        "description": "1 LP like new, Analog sound storage medium in the form of a flat disc with an inscribed, modulated spiral groove.",
        "category": "Vinyls",
        "url":["https://m.media-amazon.com/images/I/418W7MlEy9L._SX522_.jpg"]
    },
    {
        "id": 6,
        "artist": "Eagles, Don Henley",
        "title": "hotel California",
        "album": "The War",
        "price": 48.99,
        "description": "2 LP new, Analog sound storage medium in the form of a flat disc with an inscribed, modulated spiral groove.",
        "category": "Vinyls",
        "url":["https://m.media-amazon.com/images/I/41prcCWbwQL._SX300_SY300_QL70_FMwebp_.jpg"]
    },
    {
        "id": 7,
        "artist": "Bob Marley",
        "title": "The Best of Bob",
        "album": "Alone",
        "price": 23.99,
        "description": "4 LP used, 9/10 good conditions, Analog sound storage medium in the form of a flat disc with an inscribed, modulated spiral groove.",
        "category": "Vinyls",
        "url":["https://m.media-amazon.com/images/I/41WbGnfvrcL._SX300_SY300_QL70_FMwebp_.jpg"]
    },
    {
        "id": 8,
        "artist": "Pink Floyd",
        "title": "Darkside Moon",
        "album": "The War",
        "price": 33.99,
        "description": "2 LP used like new, Analog sound storage medium in the form of a flat disc with an inscribed, modulated spiral groove.",
        "category": "Vinyls",
        "url":["https://m.media-amazon.com/images/I/31+szRBlJyL._SY300_.jpg"]
    },
    {
        
        "id": 9,
        "artist": "Justin Paul",
        "title": "La la land",
        "album": "The War",
        "price": 24.99,
        "description": "4 LP used like new, Analog sound storage medium in the form of a flat disc with an inscribed, modulated spiral groove.",
        "category": "Vinyls",
        "url":["https://m.media-amazon.com/images/I/31m3UHnYFML._SX300_SY300_QL70_FMwebp_.jpg"]
    },
    {
        "id": 10,
        "artist": "Chris Stapleton",
        "title": "Traveler",
        "album": "The War",
        "price": 38.99,
        "description": "1 LP like new, Analog sound storage medium in the form of a flat disc with an inscribed, modulated spiral groove.",
        "category": "Vinyls",
        "url":["https://m.media-amazon.com/images/I/511nwyFok9L._SX300_SY300_QL70_FMwebp_.jpg"]
    },
    {
        "id": 11,
        "artist": "Kaney West",
        "title": "Dropout",
        "album": "ABS",
        "price": 49.99,
        "description": "1 LP used perfect conditions, Analog sound storage medium in the form of a flat disc with an inscribed, modulated spiral groove.",
        "category": "Vinyls",
        "url":["https://m.media-amazon.com/images/I/41STbIrHwzL._SX300_SY300_QL70_FMwebp_.jpg"]
    },
    {
        "id": 12,
        "artist": "Lorde",
        "title": "Melodrama",
        "album": "One night",
        "price": 79.99,
        "description": "2 LP new, gold edition, Analog sound storage medium in the form of a flat disc with an inscribed, modulated spiral groove.",
        "category": "Vinyls",
        "url":["https://m.media-amazon.com/images/I/41g5fLNeuML._SX300_SY300_QL70_FMwebp_.jpg"]
    },
    {
        
        "id": 13,
        "artist": "Led Zeppelin",
        "title": "Led Zeppelin",
        "album": "LP",
        "price": 44.99,
        "description": "2 LP new, unopened, Analog sound storage medium in the form of a flat disc with an inscribed, modulated spiral groove.",
        "category": "Vinyls",
        "url":["https://m.media-amazon.com/images/I/51k7TOkCNkL._SX300_SY300_QL70_FMwebp_.jpg"]
    },
    {
        "id": 14,
        "artist": "John Lennon",
        "title": "John Lennon",
        "album": "Accross Bar",
        "price": 58.99,
        "description": "2 LP used like new, Analog sound storage medium in the form of a flat disc with an inscribed, modulated spiral groove.",
        "category": "Vinyls",
        "url":["https://m.media-amazon.com/images/I/51ZnsWWUxVL._SX300_SY300_QL70_FMwebp_.jpg"]
    },
    {
        "id": 15,
        "artist": "Lana del Rey",
        "title": "Lust for Life",
        "album": "Life",
        "price": 39.99,
        "description": "1 LP used like new, Analog sound storage medium in the form of a flat disc with an inscribed, modulated spiral groove.",
        "category": "Vinyls",
        "url":["https://m.media-amazon.com/images/I/41NMhi1QTPL._SX300_SY300_QL70_FMwebp_.jpg"]
    },
    {
        "id": 16,
        "artist": "Frank Sinatra",
        "title": "Sinatra Best",
        "album": "2 FP",
        "price": 14.99,
        "description": "4 LP used, perfect conditions, Analog sound storage medium in the form of a flat disc with an inscribed, modulated spiral groove.",
        "category": "Turntables",
        "url":["https://m.media-amazon.com/images/I/51o9jtGOsHL._SX300_SY300_QL70_FMwebp_.jpg"]
    }
]
